bucketstats/__init__.py
bucketstats/discrete_distribution.py
bucketstats/probability.py
bucketstats/survival_analysis.py
bucketstats-0.3.4.dist-info/AUTHORS
bucketstats-0.3.4.dist-info/LICENSE
bucketstats-0.3.4.dist-info/METADATA
bucketstats-0.3.4.dist-info/WHEEL
bucketstats-0.3.4.dist-info/pbr.json
bucketstats-0.3.4.dist-info/top_level.txt
bucketstats-0.3.4.dist-info/RECORD
