Metadata-Version: 2.1
Name: bucketstats
Version: 0.3.4
Summary: Data analysis for bucketed data or histograms.
Home-page: https://github.com/mprelee/bucketstats
Author: Matthew Prelee
Author-email: mprelee@gmail.com
License: GPLv3.0
Project-URL: Bug Tracker, https://github.com/mprelee/bucketstats/issues
Project-URL: Documentation, https://github.com/mprelee/bucketstats
Project-URL: Source Code, https://github.com/mprelee/bucketstats
Platform: UNKNOWN
Requires-Dist: numpy
Requires-Dist: pandas
Requires-Dist: cached-property
